fortify.py
wytness.py
wytness-0.0.0.dist-info/LICENSE
wytness-0.0.0.dist-info/LICENSE-GPL
wytness-0.0.0.dist-info/LICENSE-LGPL
wytness-0.0.0.dist-info/METADATA
wytness-0.0.0.dist-info/WHEEL
wytness-0.0.0.dist-info/entry_points.txt
wytness-0.0.0.dist-info/top_level.txt
wytness-0.0.0.dist-info/RECORD
